CHANGES.rst
DESCRIPTION.rst
LICENSE
MANIFEST.in
README.md
setup.py
src/wai.annotations.commonvoice.egg-info/PKG-INFO
src/wai.annotations.commonvoice.egg-info/SOURCES.txt
src/wai.annotations.commonvoice.egg-info/dependency_links.txt
src/wai.annotations.commonvoice.egg-info/entry_points.txt
src/wai.annotations.commonvoice.egg-info/namespace_packages.txt
src/wai.annotations.commonvoice.egg-info/requires.txt
src/wai.annotations.commonvoice.egg-info/top_level.txt
src/wai/annotations/common_voice/__init__.py
src/wai/annotations/common_voice/component/_CommonVoiceReader.py
src/wai/annotations/common_voice/component/_CommonVoiceWriter.py
src/wai/annotations/common_voice/component/__init__.py
src/wai/annotations/common_voice/specifier/_CommonVoiceInputFormatSpecifier.py
src/wai/annotations/common_voice/specifier/_CommonVoiceOutputFormatSpecifier.py
src/wai/annotations/common_voice/specifier/__init__.py
src/wai/annotations/common_voice/util/_CommonVoiceDialect.py
src/wai/annotations/common_voice/util/__init__.py
src/wai/annotations/common_voice/util/_expected_header.py